{
 "months": 6,
 "impact_k": 0.5,
 "funding_mode": "storico (dove disponibile)",
 "generated_at": "2026-06-27T15:01 UTC",
 "strategies": [
  {
   "id": "tsmom-v1",
   "status": "retired",
   "thesis": "Time-series momentum (Moskowitz-Ooi-Pedersen): il segno del ritorno passato predice il ritorno futuro, su ogni asset class — l'edge istituzionale più documentato. Adattato a 1h: concordanza 7g+30g, posizionale con stop largo. Falsificata se: su basket misto crypto+commodities+ind",
   "is_benchmark": true,
   "window": "2025-12-22 → 2026-06-20",
   "basket_size": 8,
   "aggregate": {
    "mean_sharpe": -0.58,
    "mean_return": -0.0925,
    "worst_drawdown": -0.4303,
    "positive_symbols": "3/8",
    "consistency": "12/48"
   },
   "per_symbol": [
    {
     "symbol": "BTC",
     "ret": 0.072,
     "sharpe": 1.36,
     "max_dd": -0.0819,
     "trades": 22,
     "win_rate": 0.364,
     "pf": 1.52,
     "consistency": "3/6 fold positivi",
     "exits": {
      "stopped": 11,
      "target": 6,
      "closed": 5
     }
    },
    {
     "symbol": "ETH",
     "ret": 0.0859,
     "sharpe": 1.3,
     "max_dd": -0.0773,
     "trades": 31,
     "win_rate": 0.355,
     "pf": 1.51,
     "consistency": "3/6 fold positivi",
     "exits": {
      "stopped": 18,
      "target": 9,
      "closed": 4
     }
    },
    {
     "symbol": "xyz_GOLD",
     "ret": -0.0737,
     "sharpe": -0.41,
     "max_dd": -0.2404,
     "trades": 238,
     "win_rate": 0.424,
     "pf": 1.12,
     "consistency": "1/6 fold positivi",
     "exits": {
      "stopped": 128,
      "target": 79,
      "closed": 31
     }
    },
    {
     "symbol": "xyz_CL",
     "ret": -0.3982,
     "sharpe": -3.15,
     "max_dd": -0.4148,
     "trades": 290,
     "win_rate": 0.366,
     "pf": 0.83,
     "consistency": "1/6 fold positivi",
     "exits": {
      "stopped": 177,
      "target": 84,
      "closed": 29
     }
    },
    {
     "symbol": "xyz_BRENTOIL",
     "ret": -0.2917,
     "sharpe": -1.84,
     "max_dd": -0.4303,
     "trades": 336,
     "win_rate": 0.39,
     "pf": 0.97,
     "consistency": "0/6 fold positivi",
     "exits": {
      "stopped": 191,
      "target": 116,
      "closed": 29
     }
    },
    {
     "symbol": "xyz_SILVER",
     "ret": -0.2156,
     "sharpe": -1.52,
     "max_dd": -0.3254,
     "trades": 265,
     "win_rate": 0.381,
     "pf": 0.94,
     "consistency": "1/6 fold positivi",
     "exits": {
      "stopped": 153,
      "target": 81,
      "closed": 31
     }
    },
    {
     "symbol": "xyz_SP500",
     "ret": -0.302,
     "sharpe": -5.56,
     "max_dd": -0.3022,
     "trades": 156,
     "win_rate": 0.429,
     "pf": 0.88,
     "consistency": "0/6 fold positivi",
     "exits": {
      "stopped": 83,
      "target": 59,
      "closed": 14
     }
    },
    {
     "symbol": "xyz_MU",
     "ret": 0.3831,
     "sharpe": 5.2,
     "max_dd": -0.107,
     "trades": 116,
     "win_rate": 0.526,
     "pf": 1.66,
     "consistency": "3/6 fold positivi",
     "exits": {
      "target": 53,
      "stopped": 51,
      "closed": 12
     }
    }
   ]
  },
  {
   "id": "highvol-port-v1",
   "status": "challenger",
   "engine": "portfolio",
   "thesis": "HIGH-VOL ANOMALY (inverso della classica low-vol anomaly). Nel basket crypto, gli asset PIU' VOLATILI delle ultime 72h sovraperformano i piu' calmi su orizzonti medi. E' ortogonale al momentum: ranka la VOLATILITA' (dev standard dei rendimenti), non il rendimento stesso. Tesi: il",
   "is_benchmark": false,
   "window": "2025-12-22 → 2026-06-20",
   "basket_size": 9,
   "vol_target": "off",
   "aggregate": {
    "mean_sharpe": 2.07,
    "mean_return": 0.3533,
    "worst_drawdown": -0.1463,
    "positive_symbols": "market-neutral",
    "consistency": "4/6 fold positivi"
   },
   "per_symbol": []
  },
  {
   "id": "xsmom-highvol-combo-v1",
   "status": "challenger",
   "engine": "portfolio",
   "thesis": "COMBO dei DUE edge ortogonali forti del progetto: xsmom (momentum relativo, corr al beta comune nettato) + HIGH-VOL (risk premium crypto, long alt volatili). I due fattori hanno correlazione rendimenti +0.28 (diversificazione GENUINA, non ridondanza: le varianti xsmom erano corr ",
   "is_benchmark": false,
   "window": "2025-12-22 → 2026-06-20",
   "basket_size": 9,
   "vol_target": "off",
   "aggregate": {
    "mean_sharpe": 1.94,
    "mean_return": 0.2896,
    "worst_drawdown": -0.1268,
    "positive_symbols": "market-neutral",
    "consistency": "3/6 fold positivi"
   },
   "per_symbol": []
  },
  {
   "id": "xsmom-highvol-voltarget-v1",
   "status": "challenger",
   "engine": "portfolio",
   "thesis": "COMBO 50/50 dei due edge ortogonali (xsmom + highvol, corr 0.28) con VOL-TARGET OVERLAY (Moreira-Muir \"Volatility-Managed Portfolios\" 2017). Il blend-ratio sweep dell'audit di robustezza ha mostrato 50/50 marginalmente > del 70/30 scelto in xsmom-highvol-combo-v1 (Sharpe 2.75 vs ",
   "is_benchmark": false,
   "window": "2025-12-22 → 2026-06-20",
   "basket_size": 9,
   "vol_target": "on (m medio 0.89)",
   "aggregate": {
    "mean_sharpe": 1.97,
    "mean_return": 0.2218,
    "worst_drawdown": -0.1158,
    "positive_symbols": "market-neutral",
    "consistency": "3/6 fold positivi"
   },
   "per_symbol": []
  },
  {
   "id": "xsmom-multihorizon-v1",
   "status": "challenger",
   "engine": "portfolio",
   "thesis": "CROSS-SECTIONAL MOMENTUM MULTI-ORIZZONTE. Stesso edge del parent xsmom-port-v1 (rank relativo nel basket, dollar-neutral) ma mediato su 3 orizzonti (lb 96/168/336h): il segnale a 96h cattura i movimenti di medio termine, 168h e' il core del parent, 336h il trend di fondo. La medi",
   "is_benchmark": false,
   "window": "2025-12-22 → 2026-06-20",
   "basket_size": 9,
   "vol_target": "off",
   "aggregate": {
    "mean_sharpe": 2.07,
    "mean_return": 0.3039,
    "worst_drawdown": -0.1185,
    "positive_symbols": "market-neutral",
    "consistency": "4/6 fold positivi"
   },
   "per_symbol": []
  },
  {
   "id": "xsmom-port-v1",
   "status": "challenger",
   "engine": "portfolio",
   "thesis": "Cross-sectional momentum a PORTAFOGLIO: long il top-terzile del basket per forza relativa (ultime 168h), short il bottom-terzile, dollar-neutral, ribilanciato ogni 168h. Lo stesso edge che da -14.5% nell'engine per-simbolo stop-based (l'IC e troppo sottile per trade discreti) ren",
   "is_benchmark": false,
   "window": "2025-12-22 → 2026-06-20",
   "basket_size": 9,
   "vol_target": "off",
   "aggregate": {
    "mean_sharpe": 1.97,
    "mean_return": 0.2943,
    "worst_drawdown": -0.1199,
    "positive_symbols": "market-neutral",
    "consistency": "3/6 fold positivi"
   },
   "per_symbol": []
  }
 ]
}